rfilerunner/__init__.py
rfilerunner/colors.py
rfilerunner/parse.py
rfilerunner/run.py
rfilerunner/runners.py
rfilerunner/util.py
rfilerunner-0.1.6.dist-info/LICENSE
rfilerunner-0.1.6.dist-info/METADATA
rfilerunner-0.1.6.dist-info/WHEEL
rfilerunner-0.1.6.dist-info/entry_points.txt
rfilerunner-0.1.6.dist-info/top_level.txt
rfilerunner-0.1.6.dist-info/RECORD
