Metadata-Version: 2.1
Name: rfilerunner
Version: 0.1.6
Summary: a simple command runner
Home-page: https://github.com/goatmobile/rfilerunner
Author: goatmobile
Classifier: Programming Language :: Python :: 3
Classifier: License :: OSI Approved :: MIT License
Classifier: Operating System :: OS Independent
Requires-Python: >=3.7
License-File: LICENSE
Requires-Dist: Click
Requires-Dist: PyYAML
Requires-Dist: watchdog
